muzik_api/__init__.py
muzik_api/asgi.py
muzik_api/settings.py
muzik_api/urls.py
muzik_api/wsgi.py
muzik_api-0.1.0.dist-info/METADATA
muzik_api-0.1.0.dist-info/WHEEL
muzik_api-0.1.0.dist-info/RECORD
